cec2rs232/__init__.py
cec2rs232/cec.py
cec2rs232/main.py
cec2rs232/mqtt.py
cec2rs232/driver/__init__.py
cec2rs232/driver/base.py
cec2rs232/driver/base_ir.py
cec2rs232/driver/base_serial.py
cec2rs232/driver/cambridge_cxa61.py
cec2rs232/driver/registry.py
cec2rs232-0.4.0.dist-info/licenses/LICENSE.md
cec2rs232-0.4.0.dist-info/METADATA
cec2rs232-0.4.0.dist-info/WHEEL
cec2rs232-0.4.0.dist-info/entry_points.txt
cec2rs232-0.4.0.dist-info/top_level.txt
cec2rs232-0.4.0.dist-info/RECORD
