Metadata-Version: 2.4
Name: cec2rs232
Version: 0.4.0
Summary: Enables a Raspberry Pi to act as a bridge between CEC and RS-232 or IR
Home-page: https://github.com/tmick0/cec2rs232
Author: travis mick
Author-email: root@lo.calho.st
License: MIT
Requires-Python: >=3.9
License-File: LICENSE.md
Requires-Dist: pycec
Requires-Dist: pyserial
Requires-Dist: piir
Requires-Dist: aiomqtt
Dynamic: author
Dynamic: author-email
Dynamic: description
Dynamic: description-content-type
Dynamic: home-page
Dynamic: license
Dynamic: license-file
Dynamic: requires-dist
Dynamic: requires-python
Dynamic: summary
